functions_framework_test-3.1.1-py3.7-nspkg.pth
functions_framework/__init__.py
functions_framework/__main__.py
functions_framework/_cli.py
functions_framework/_function_registry.py
functions_framework/background_event.py
functions_framework/event_conversion.py
functions_framework/exceptions.py
functions_framework/_http/__init__.py
functions_framework/_http/flask.py
functions_framework/_http/gunicorn.py
google/cloud/functions/__init__.py
google/cloud/functions/context.py
google/cloud/functions_v1/__init__.py
google/cloud/functions_v1/context.py
google/cloud/functions_v1beta2/__init__.py
google/cloud/functions_v1beta2/context.py
openfunction/__init__.py
openfunction/async_server.py
openfunction/dapr_output_middleware.py
openfunction/function_context.py
openfunction/function_runtime.py
functions_framework_test-3.1.1.dist-info/LICENSE
functions_framework_test-3.1.1.dist-info/METADATA
functions_framework_test-3.1.1.dist-info/WHEEL
functions_framework_test-3.1.1.dist-info/entry_points.txt
functions_framework_test-3.1.1.dist-info/namespace_packages.txt
functions_framework_test-3.1.1.dist-info/top_level.txt
functions_framework_test-3.1.1.dist-info/RECORD
